impdata/__init__.py
impdata/impdata.py
impdata-0.0.3.dist-info/LICENSE
impdata-0.0.3.dist-info/METADATA
impdata-0.0.3.dist-info/WHEEL
impdata-0.0.3.dist-info/top_level.txt
impdata-0.0.3.dist-info/RECORD
