Metadata-Version: 2.1
Name: impdata
Version: 0.0.3
Summary: A tool for load  data into postgresql/mysql
Home-page: https://github.com/FutureNear/impdata.git
Author: FutureNear
Author-email: futurenear@163.com
License: UNKNOWN
Platform: UNKNOWN
Classifier: Programming Language :: Python :: 3
Classifier: License :: OSI Approved :: MIT License
Classifier: Operating System :: OS Independent
Requires-Python: >=3.6
License-File: LICENSE
Requires-Dist: gtls (>=0.0.1)
